[
  { "label": "Fantasy", "value": "fantasy" },
  { "label": "Fiction", "value": "fiction" },
  { "label": "Classics", "value": "classics" },
  { "label": "Adventure", "value": "adventure" },
  { "label": "Science Fiction Fantasy", "value": "science fiction fantasy" },
  { "label": "Epic Fantasy", "value": "epic fantasy" },
  { "label": "High Fantasy", "value": "high fantasy" },
  { "label": "Young Adult", "value": "young adult" },
  { "label": "Literature", "value": "literature" },
  { "label": "Magic", "value": "magic" },
  { "label": "Romance", "value": "romance" },
  { "label": "Time Travel", "value": "time travel" },
  { "label": "Science Fiction", "value": "science fiction" },
  { "label": "Contemporary", "value": "contemporary" },
  { "label": "Adult", "value": "adult" },
  { "label": "Chick Lit", "value": "chick lit" },
  { "label": "Adult Fiction", "value": "adult fiction" },
  { "label": "Magical Realism", "value": "magical realism" },
  { "label": "Humor", "value": "humor" },
  { "label": "Comedy", "value": "comedy" },
  { "label": "Audiobook", "value": "audiobook" },
  { "label": "Novels", "value": "novels" },
  { "label": "Historical Fiction", "value": "historical fiction" },
  { "label": "Gothic", "value": "gothic" },
  { "label": "Historical", "value": "historical" },
  { "label": "19th Century", "value": "19th century" },
  { "label": "School", "value": "school" },
  { "label": "Classic Literature", "value": "classic literature" },
  { "label": "Horror", "value": "horror" },
  { "label": "Post Apocalyptic", "value": "post apocalyptic" },
  { "label": "Thriller", "value": "thriller" },
  { "label": "Dystopia", "value": "dystopia" },
  { "label": "Apocalyptic", "value": "apocalyptic" },
  { "label": "Russia", "value": "russia" },
  { "label": "Russian Literature", "value": "russian literature" },
  { "label": "Feminism", "value": "feminism" },
  { "label": "LGBT", "value": "lgbt" },
  { "label": "African American", "value": "african american" },
  { "label": "Africa", "value": "africa" },
  { "label": "Literary Fiction", "value": "literary fiction" },
  { "label": "Religion", "value": "religion" },
  { "label": "Childrens", "value": "childrens" },
  { "label": "Middle Grade", "value": "middle grade" },
  { "label": "Coming Of Age", "value": "coming of age" },
  { "label": "American", "value": "american" },
  { "label": "20th Century", "value": "20th century" },
  { "label": "Epic", "value": "epic" },
  { "label": "Juvenile", "value": "juvenile" },
  { "label": "Drama", "value": "drama" },
  { "label": "Mystery", "value": "mystery" },
  { "label": "Suspense", "value": "suspense" },
  { "label": "Mystery Thriller", "value": "mystery thriller" },
  { "label": "Crime", "value": "crime" },
  { "label": "Modern Classics", "value": "modern classics" },
  { "label": "Nonfiction", "value": "nonfiction" },
  { "label": "Memoir", "value": "memoir" },
  { "label": "Biography", "value": "biography" },
  { "label": "Ireland", "value": "ireland" },
  { "label": "Autobiography", "value": "autobiography" },
  { "label": "Biography Memoir", "value": "biography memoir" },
  { "label": "History", "value": "history" },
  { "label": "Irish Literature", "value": "irish literature" },
  { "label": "Vampires", "value": "vampires" },
  { "label": "Paranormal", "value": "paranormal" },
  { "label": "Supernatural", "value": "supernatural" },
  { "label": "Urban Fantasy", "value": "urban fantasy" },
  { "label": "Inspirational", "value": "inspirational" },
  { "label": "Philosophy", "value": "philosophy" },
  { "label": "Self Help", "value": "self help" },
  { "label": "Angels", "value": "angels" },
  { "label": "Paranormal Romance", "value": "paranormal romance" },
  { "label": "Young Adult Fantasy", "value": "young adult fantasy" },
  { "label": "Teen", "value": "teen" },
  { "label": "Action", "value": "action" },
  { "label": "France", "value": "france" },
  { "label": "French Literature", "value": "french literature" },
  { "label": "Read For School", "value": "read for school" },
  { "label": "High School", "value": "high school" },
  { "label": "Medieval", "value": "medieval" },
  { "label": "British Literature", "value": "british literature" },
  { "label": "Italian Literature", "value": "italian literature" },
  { "label": "Italy", "value": "italy" },
  { "label": "Westerns", "value": "westerns" },
  { "label": "Realistic Fiction", "value": "realistic fiction" },
  { "label": "Love", "value": "love" },
  { "label": "Mental Health", "value": "mental health" },
  { "label": "Psychology", "value": "psychology" },
  { "label": "Mental Illness", "value": "mental illness" },
  { "label": "Poetry", "value": "poetry" },
  { "label": "Book Club", "value": "book club" },
  { "label": "Women's", "value": "women's" },
  { "label": "Queer", "value": "queer" },
  { "label": "German Literature", "value": "german literature" },
  { "label": "Contemporary Romance", "value": "contemporary romance" },
  { "label": "Picture Books", "value": "picture books" },
  { "label": "Christmas", "value": "christmas" },
  { "label": "Holiday", "value": "holiday" },
  { "label": "Kids", "value": "kids" }
]
